odoo9_addon_crm_deduplicate_by_ref-9.0.1.0.0-py2.7-nspkg.pth
odoo_addons/crm_deduplicate_by_ref/__openerp__.py
odoo_addons/crm_deduplicate_by_ref/__init__.py
odoo_addons/crm_deduplicate_by_ref/README.rst
odoo_addons/crm_deduplicate_by_ref/i18n/es.po
odoo_addons/crm_deduplicate_by_ref/wizards/partner_merge.py
odoo_addons/crm_deduplicate_by_ref/wizards/__init__.py
odoo_addons/crm_deduplicate_by_ref/wizards/partner_merge_view.xml
odoo_addons/crm_deduplicate_by_ref/tests/__init__.py
odoo_addons/crm_deduplicate_by_ref/tests/test_crm_deduplicate_by_ref.py
odoo_addons/crm_deduplicate_by_ref/static/description/icon.svg
odoo_addons/crm_deduplicate_by_ref/static/description/icon.png
odoo9_addon_crm_deduplicate_by_ref-9.0.1.0.0.dist-info/top_level.txt
odoo9_addon_crm_deduplicate_by_ref-9.0.1.0.0.dist-info/WHEEL
odoo9_addon_crm_deduplicate_by_ref-9.0.1.0.0.dist-info/RECORD
odoo9_addon_crm_deduplicate_by_ref-9.0.1.0.0.dist-info/metadata.json
odoo9_addon_crm_deduplicate_by_ref-9.0.1.0.0.dist-info/DESCRIPTION.rst
odoo9_addon_crm_deduplicate_by_ref-9.0.1.0.0.dist-info/METADATA
odoo9_addon_crm_deduplicate_by_ref-9.0.1.0.0.dist-info/namespace_packages.txt
